PyCCWF/__init__.py
PyCCWF/data_generation/__init__.py
PyCCWF/data_generation/cluster_generator.py
PyCCWF/data_generation/simulation.py
PyCCWF/models/__init__.py
PyCCWF/models/clustering.py
PyCCWF/models/forest.py
PyCCWF/models/stacking.py
PyCCWF/models/wrapper.py
PyCCWF/visualization/__init__.py
PyCCWF/visualization/plots.py
examples/__init__.py
examples/multiple_clusters_example.py
examples/single_dataset_example.py
PyCCWF-0.1.2.dist-info/LICENSE
PyCCWF-0.1.2.dist-info/METADATA
PyCCWF-0.1.2.dist-info/WHEEL
PyCCWF-0.1.2.dist-info/top_level.txt
PyCCWF-0.1.2.dist-info/RECORD
