Metadata-Version: 2.1
Name: PyCCWF
Version: 0.1.2
Summary: Implementation of Cross-cluster Weighted Forests
Author: Maya Ramchandran
Requires-Python: >=3.7
License-File: LICENSE
Requires-Dist: numpy
Requires-Dist: pandas
Requires-Dist: scikit-learn
Requires-Dist: scipy
Requires-Dist: matplotlib
